nvidia_binarchive/parse_redist.py
nvidia_binarchive-0.5.0.dist-info/METADATA
nvidia_binarchive-0.5.0.dist-info/WHEEL
nvidia_binarchive-0.5.0.dist-info/entry_points.txt
nvidia_binarchive-0.5.0.dist-info/licenses/LICENSE
nvidia_binarchive-0.5.0.dist-info/RECORD
